searchview/__init__.py
searchview/forms.py
searchview/views.py
django_searchview_lib-1.0.5.dist-info/LICENSE
django_searchview_lib-1.0.5.dist-info/METADATA
django_searchview_lib-1.0.5.dist-info/WHEEL
django_searchview_lib-1.0.5.dist-info/top_level.txt
django_searchview_lib-1.0.5.dist-info/RECORD
