Metadata-Version: 2.1
Name: django-searchview-lib
Version: 1.0.5
Summary: SearchView is a multiple inheritance class of FormView and ListView
Home-page: https://github.com/Arisophy/django-searchview
Author: Arisophy
Author-email: arisophy@is-jpn.com
License: UNKNOWN
Platform: UNKNOWN
Classifier: Programming Language :: Python :: 3
Classifier: License :: OSI Approved :: MIT License
Classifier: Operating System :: OS Independent
Classifier: Development Status :: 5 - Production/Stable
Classifier: Framework :: Django
Requires-Python: >=3.6
